{"v":"5.12.1","fr":60,"ip":0,"op":90,"w":430,"h":430,"nm":"wired-flat-3136-big-shop","ddd":0,"assets":[{"id":"comp_1","nm":"hover-pinch","fr":60,"layers":[{"ddd":0,"ind":1,"ty":4,"nm":"Subtract 5","sr":1,"ks":{"o":{"a":0,"k":30,"ix":11},"r":{"a":0,"k":0,"ix":10},"p":{"a":0,"k":[84.891,232.506,0],"ix":2,"l":2},"a":{"a":0,"k":[0,0,0],"ix":1,"l":2},"s":{"a":0,"k":[100,100,100],"ix":6,"l":2}},"ao":0,"shapes":[{"ty":"gr","it":[{"ind":0,"ty":"sh","ix":1,"ks":{"a":0,"k":{"i":[[0,0],[0,0],[0,0],[0,0]],"o":[[0,0],[0,0],[0,0],[0,0]],"v":[[16.062,-17.506],[3.938,17.506],[-16.062,17.506],[-3.938,-17.506]],"c":true},"ix":2},"nm":"Path 1","mn":"ADBE Vector Shape - Group","hd":false},{"ty":"fl","c":{"a":0,"k":[0.922,0.902,0.937,1],"ix":4,"x":"var $bm_rt;\n$bm_rt = comp('wired-flat-3136-big-shop').layer('control').effect('primary')('Color');"},"o":{"a":0,"k":100,"ix":5},"r":1,"bm":0,"nm":".primary","mn":"ADBE Vector Graphic - Fill","hd":false,"cl":"primary"},{"ty":"tr","p":{"a":0,"k":[0,0],"ix":2},"a":{"a":0,"k":[0,0],"ix":1},"s":{"a":0,"k":[100,100],"ix":3},"r":{"a":0,"k":0,"ix":6},"o":{"a":0,"k":100,"ix":7},"sk":{"a":0,"k":0,"ix":4},"sa":{"a":0,"k":0,"ix":5},"nm":"Transform"}],"nm":"Subtract","np":2,"cix":2,"bm":0,"ix":1,"mn":"ADBE Vector Group","hd":false}],"ip":0,"op":300,"st":0,"ct":1,"bm":1},{"ddd":0,"ind":3,"ty":4,"nm":"Subtract 6","sr":1,"ks":{"o":{"a":0,"k":50,"ix":11},"r":{"a":0,"k":0,"ix":10},"p":{"a":0,"k":[91.038,203.5,0],"ix":2,"l":2},"a":{"a":0,"k":[0,0,0],"ix":1,"l":2},"s":{"a":0,"k":[100,100,100],"ix":6,"l":2}},"ao":0,"shapes":[{"ty":"gr","it":[{"ind":0,"ty":"sh","ix":1,"ks":{"a":0,"k":{"i":[[0,0],[0,0],[0,0],[0,0]],"o":[[0,0],[0,0],[0,0],[0,0]],"v":[[-10,-9],[10,-9],[10,12.75],[-10,12.75]],"c":true},"ix":2},"nm":"Path 1","mn":"ADBE Vector Shape - Group","hd":false},{"ty":"fl","c":{"a":0,"k":[0.227,0.2,0.278,1],"ix":4,"x":"var $bm_rt;\n$bm_rt = comp('wired-flat-3136-big-shop').layer('control').effect('secondary')('Color');"},"o":{"a":0,"k":100,"ix":5},"r":1,"bm":0,"nm":".secondary","mn":"ADBE Vector Graphic - Fill","hd":false,"cl":"secondary"},{"ty":"tr","p":{"a":0,"k":[0,0],"ix":2},"a":{"a":0,"k":[0,0],"ix":1},"s":{"a":0,"k":[100,100],"ix":3},"r":{"a":0,"k":0,"ix":6},"o":{"a":0,"k":100,"ix":7},"sk":{"a":0,"k":0,"ix":4},"sa":{"a":0,"k":0,"ix":5},"nm":"Transform"}],"nm":"Subtract","np":2,"cix":2,"bm":0,"ix":1,"mn":"ADBE Vector Group","hd":false}],"ip":0,"op":300,"st":0,"ct":1,"bm":1},{"ddd":0,"ind":4,"ty":4,"nm":"Rectangle 92","sr":1,"ks":{"o":{"a":0,"k":100,"ix":11},"r":{"a":0,"k":0,"ix":10},"p":{"a":0,"k":[215.539,203.5,0],"ix":2,"l":2},"a":{"a":0,"k":[0,0,0],"ix":1,"l":2},"s":{"a":0,"k":[100,100,100],"ix":6,"l":2}},"ao":0,"shapes":[{"ty":"gr","it":[{"ind":0,"ty":"sh","ix":1,"ks":{"a":0,"k":{"i":[[0,0],[0,0],[0,0],[0,0]],"o":[[0,0],[0,0],[0,0],[0,0]],"v":[[133.251,-9.125],[-134.501,-9],[-134.501,13.375],[133.251,13.25]],"c":true},"ix":2},"nm":"Path 1","mn":"ADBE Vector Shape - Group","hd":false},{"ty":"fl","c":{"a":0,"k":[0.227,0.2,0.278,1],"ix":4,"x":"var $bm_rt;\n$bm_rt = comp('wired-flat-3136-big-shop').layer('control').effect('secondary')('Color');"},"o":{"a":0,"k":100,"ix":5},"r":1,"bm":0,"nm":".secondary","mn":"ADBE Vector Graphic - Fill","hd":false,"cl":"secondary"},{"ty":"tr","p":{"a":0,"k":[0,0],"ix":2},"a":{"a":0,"k":[0,0],"ix":1},"s":{"a":0,"k":[100,100],"ix":3},"r":{"a":0,"k":0,"ix":6},"o":{"a":0,"k":100,"ix":7},"sk":{"a":0,"k":0,"ix":4},"sa":{"a":0,"k":0,"ix":5},"nm":"Transform"}],"nm":"Rectangle 90","np":2,"cix":2,"bm":0,"ix":1,"mn":"ADBE Vector Group","hd":false}],"ip":0,"op":300,"st":0,"ct":1,"bm":0},{"ddd":0,"ind":5,"ty":4,"nm":"Roof fill 2","parent":7,"sr":1,"ks":{"o":{"a":0,"k":50,"ix":11},"r":{"a":0,"k":0,"ix":10},"p":{"a":0,"k":[0,195.433,0],"ix":2,"l":2},"a":{"a":0,"k":[0,133.433,0],"ix":1,"l":2},"s":{"a":0,"k":[100,100,100],"ix":6,"l":2}},"ao":0,"hasMask":true,"masksProperties":[{"inv":false,"mode":"s","pt":{"a":0,"k":{"i":[[0,0],[0,0],[0,0],[0,0]],"o":[[0,0],[0,0],[0,0],[0,0]],"v":[[175.5,-102.75],[-167,-102.75],[-167,-53.75],[175.5,-53.75]],"c":true},"ix":1},"o":{"a":0,"k":100,"ix":3},"x":{"a":0,"k":0,"ix":4},"nm":"Mask 1"}],"shapes":[{"ty":"gr","it":[{"ind":0,"ty":"sh","ix":1,"ks":{"a":1,"k":[{"i":{"x":0.35,"y":1},"o":{"x":0.333,"y":0},"t":5,"s":[{"i":[[0,0],[0,0],[-16.133,0],[0,16.133],[0,0]],"o":[[0,0],[0,16.133],[16.133,0],[0,0],[0,0]],"v":[[-80.118,-88.5],[-87.474,-53.404],[-58.512,-24.942],[-29.3,-53.404],[-26.681,-88.75]],"c":false}]},{"i":{"x":0.667,"y":1},"o":{"x":0.65,"y":0},"t":16,"s":[{"i":[[0,0],[0,0],[-16.133,0],[0,16.133],[0,0]],"o":[[0,0],[0,21.404],[16.133,0],[0,0],[0,0]],"v":[[-80.118,-88.5],[-87.474,-53.404],[-58.448,-14.942],[-29.3,-53.404],[-26.681,-88.75]],"c":false}]},{"i":{"x":0.667,"y":1},"o":{"x":0.333,"y":0},"t":35.059,"s":[{"i":[[0,0],[0,0],[-16.133,0],[0,16.133],[0,0]],"o":[[0,0],[0,16.133],[16.133,0],[0,0],[0,0]],"v":[[-80.118,-88.5],[-87.474,-53.404],[-58.512,-31.942],[-29.3,-53.404],[-26.681,-88.75]],"c":false}]},{"i":{"x":0.667,"y":1},"o":{"x":0.333,"y":0},"t":51.734,"s":[{"i":[[0,0],[0,0],[-16.133,0],[0,16.133],[0,0]],"o":[[0,0],[0,16.133],[16.133,0],[0,0],[0,0]],"v":[[-80.118,-88.5],[-87.474,-53.404],[-58.512,-21.942],[-29.3,-53.404],[-26.681,-88.75]],"c":false}]},{"i":{"x":0.667,"y":1},"o":{"x":0.333,"y":0},"t":68,"s":[{"i":[[0,0],[0,0],[-16.133,0],[0,16.133],[0,0]],"o":[[0,0],[0,16.133],[16.133,0],[0,0],[0,0]],"v":[[-80.118,-88.5],[-87.474,-53.404],[-58.512,-26.942],[-29.3,-53.404],[-26.681,-88.75]],"c":false}]},{"t":84,"s":[{"i":[[0,0],[0,0],[-16.133,0],[0,16.133],[0,0]],"o":[[0,0],[0,16.133],[16.133,0],[0,0],[0,0]],"v":[[-80.118,-88.5],[-87.474,-53.404],[-58.512,-24.942],[-29.3,-53.404],[-26.681,-88.75]],"c":false}]}],"ix":2},"nm":"Path 1","mn":"ADBE Vector Shape - Group","hd":false},{"ty":"fl","c":{"a":0,"k":[0.573,0.078,0.047,1],"ix":4,"x":"var $bm_rt;\n$bm_rt = comp('wired-flat-3136-big-shop').layer('control').effect('quaternary')('Color');"},"o":{"a":0,"k":100,"ix":5},"r":1,"bm":0,"nm":".quaternary","mn":"ADBE Vector Graphic - Fill","hd":false,"cl":"quaternary"},{"ty":"tr","p":{"a":0,"k":[0,0],"ix":2},"a":{"a":0,"k":[0,0],"ix":1},"s":{"a":0,"k":[100,100],"ix":3},"r":{"a":0,"k":0,"ix":6},"o":{"a":0,"k":100,"ix":7},"sk":{"a":0,"k":0,"ix":4},"sa":{"a":0,"k":0,"ix":5},"nm":"Transform"}],"nm":"Group 1","np":3,"cix":2,"bm":0,"ix":1,"mn":"ADBE Vector Group","hd":false},{"ty":"gr","it":[{"ind":0,"ty":"sh","ix":1,"ks":{"a":1,"k":[{"i":{"x":0.35,"y":1},"o":{"x":0.333,"y":0},"t":5,"s":[{"i":[[0,0],[0,0],[-16.133,0],[0,16.133],[0,0]],"o":[[0,0],[0,16.133],[16.133,0],[0,0],[0,0]],"v":[[26.256,-88.25],[29.124,-53.404],[58.336,-24.692],[86.049,-53.404],[78.443,-88.5]],"c":false}]},{"i":{"x":0.667,"y":1},"o":{"x":0.65,"y":0},"t":16,"s":[{"i":[[0,0],[0,0],[-16.133,0],[0,16.133],[0,0]],"o":[[0,0],[0,16.133],[16.133,0],[0,0],[0,0]],"v":[[26.256,-88.25],[29.124,-53.404],[58.4,-14.692],[86.049,-53.404],[78.443,-88.5]],"c":false}]},{"i":{"x":0.667,"y":1},"o":{"x":0.333,"y":0},"t":35.059,"s":[{"i":[[0,0],[0,0],[-16.133,0],[0,16.133],[0,0]],"o":[[0,0],[0,16.133],[16.133,0],[0,0],[0,0]],"v":[[26.256,-88.25],[29.124,-53.404],[58.336,-31.692],[86.049,-53.404],[78.443,-88.5]],"c":false}]},{"i":{"x":0.667,"y":1},"o":{"x":0.333,"y":0},"t":51.734,"s":[{"i":[[0,0],[0,0],[-16.133,0],[0,16.133],[0,0]],"o":[[0,0],[0,16.133],[16.133,0],[0,0],[0,0]],"v":[[26.256,-88.25],[29.124,-53.404],[58.336,-21.692],[86.049,-53.404],[78.443,-88.5]],"c":false}]},{"i":{"x":0.667,"y":1},"o":{"x":0.333,"y":0},"t":68,"s":[{"i":[[0,0],[0,0],[-16.133,0],[0,16.133],[0,0]],"o":[[0,0],[0,16.133],[16.133,0],[0,0],[0,0]],"v":[[26.256,-88.25],[29.124,-53.404],[58.336,-26.692],[86.049,-53.404],[78.443,-88.5]],"c":false}]},{"t":84,"s":[{"i":[[0,0],[0,0],[-16.133,0],[0,16.133],[0,0]],"o":[[0,0],[0,16.133],[16.133,0],[0,0],[0,0]],"v":[[26.256,-88.25],[29.124,-53.404],[58.336,-24.692],[86.049,-53.404],[78.443,-88.5]],"c":false}]}],"ix":2},"nm":"Path 1","mn":"ADBE Vector Shape - Group","hd":false},{"ty":"fl","c":{"a":0,"k":[0.573,0.078,0.047,1],"ix":4,"x":"var $bm_rt;\n$bm_rt = comp('wired-flat-3136-big-shop').layer('control').effect('quaternary')('Color');"},"o":{"a":0,"k":100,"ix":5},"r":1,"bm":0,"nm":".quaternary","mn":"ADBE Vector Graphic - Fill","hd":false,"cl":"quaternary"},{"ty":"tr","p":{"a":0,"k":[0,0],"ix":2},"a":{"a":0,"k":[0,0],"ix":1},"s":{"a":0,"k":[100,100],"ix":3},"r":{"a":0,"k":0,"ix":6},"o":{"a":0,"k":100,"ix":7},"sk":{"a":0,"k":0,"ix":4},"sa":{"a":0,"k":0,"ix":5},"nm":"Transform"}],"nm":"Group 2","np":3,"cix":2,"bm":0,"ix":2,"mn":"ADBE Vector Group","hd":false},{"ty":"gr","it":[{"ind":0,"ty":"sh","ix":1,"ks":{"a":1,"k":[{"i":{"x":0.35,"y":1},"o":{"x":0.333,"y":0},"t":0,"s":[{"i":[[0,-16.133],[16.133,0],[0,16.133]],"o":[[0,16.133],[-16.133,0],[0,-16.133]],"v":[[29.124,-53.404],[-0.088,-24.192],[-29.3,-53.404]],"c":false}]},{"i":{"x":0.667,"y":1},"o":{"x":0.65,"y":0},"t":11,"s":[{"i":[[0,-16.133],[16.133,0],[0,16.133]],"o":[[0,16.133],[-16.133,0],[0,-16.133]],"v":[[29.124,-53.404],[-0.024,-14.192],[-29.3,-53.404]],"c":false}]},{"i":{"x":0.667,"y":1},"o":{"x":0.333,"y":0},"t":30.059,"s":[{"i":[[0,-16.133],[16.133,0],[0,16.133]],"o":[[0,16.133],[-16.133,0],[0,-16.133]],"v":[[29.124,-53.404],[-0.088,-31.192],[-29.3,-53.404]],"c":false}]},{"i":{"x":0.667,"y":1},"o":{"x":0.333,"y":0},"t":46.734,"s":[{"i":[[0,-16.133],[16.133,0],[0,16.133]],"o":[[0,16.133],[-16.133,0],[0,-16.133]],"v":[[29.124,-53.404],[-0.088,-21.192],[-29.3,-53.404]],"c":false}]},{"i":{"x":0.667,"y":1},"o":{"x":0.333,"y":0},"t":63,"s":[{"i":[[0,-16.133],[16.133,0],[0,16.133]],"o":[[0,16.133],[-16.133,0],[0,-16.133]],"v":[[29.124,-53.404],[-0.088,-26.192],[-29.3,-53.404]],"c":false}]},{"t":79,"s":[{"i":[[0,-16.133],[16.133,0],[0,16.133]],"o":[[0,16.133],[-16.133,0],[0,-16.133]],"v":[[29.124,-53.404],[-0.088,-24.192],[-29.3,-53.404]],"c":false}]}],"ix":2},"nm":"Path 1","mn":"ADBE Vector Shape - Group","hd":false},{"ty":"fl","c":{"a":0,"k":[0.922,0.902,0.937,1],"ix":4,"x":"var $bm_rt;\n$bm_rt = comp('wired-flat-3136-big-shop').layer('control').effect('primary')('Color');"},"o":{"a":0,"k":100,"ix":5},"r":1,"bm":0,"nm":".primary","mn":"ADBE Vector Graphic - Fill","hd":false,"cl":"primary"},{"ty":"tr","p":{"a":0,"k":[0,0],"ix":2},"a":{"a":0,"k":[0,0],"ix":1},"s":{"a":0,"k":[100,100],"ix":3},"r":{"a":0,"k":0,"ix":6},"o":{"a":0,"k":100,"ix":7},"sk":{"a":0,"k":0,"ix":4},"sa":{"a":0,"k":0,"ix":5},"nm":"Transform"}],"nm":"Group 3","np":3,"cix":2,"bm":0,"ix":3,"mn":"ADBE Vector Group","hd":false},{"ty":"gr","it":[{"ind":0,"ty":"sh","ix":1,"ks":{"a":1,"k":[{"i":{"x":0.35,"y":1},"o":{"x":0.333,"y":0},"t":10,"s":[{"i":[[0,-16.133],[16.133,0],[0,16.133],[0,0],[0,0],[0,0],[16.133,0],[4.451,16.904]],"o":[[0,16.133],[-16.133,0],[0,0],[0,0],[0,0],[0,16.133],[-16.133,0],[-4.108,-15.602]],"v":[[-87.474,-53.404],[-116.936,-24.192],[-146.148,-53.404],[-133.805,-89.5],[132.629,-89.5],[145.723,-54.154],[117.011,-24.192],[86.049,-53.404]],"c":false}]},{"i":{"x":0.667,"y":1},"o":{"x":0.65,"y":0},"t":21,"s":[{"i":[[0,-16.133],[16.133,0],[0,22.404],[0,0],[0,0],[0,0],[16.133,0],[4.451,16.904]],"o":[[0,16.133],[-16.133,0],[0,0],[0,0],[0,0],[0,22.154],[-16.133,0],[-4.108,-15.602]],"v":[[-87.474,-53.404],[-116.873,-14.192],[-146.148,-53.404],[-133.805,-89.5],[132.629,-89.5],[145.723,-54.154],[117.074,-14.192],[86.049,-53.404]],"c":false}]},{"i":{"x":0.667,"y":1},"o":{"x":0.333,"y":0},"t":40.059,"s":[{"i":[[0,-16.133],[16.133,0],[0,16.133],[0,0],[0,0],[0,0],[16.133,0],[4.451,16.904]],"o":[[0,16.133],[-16.133,0],[0,0],[0,0],[0,0],[0,16.133],[-16.133,0],[-4.108,-15.602]],"v":[[-87.474,-53.404],[-116.936,-31.192],[-146.148,-53.404],[-133.805,-89.5],[132.629,-89.5],[145.723,-54.154],[117.011,-31.192],[86.049,-53.404]],"c":false}]},{"i":{"x":0.667,"y":1},"o":{"x":0.333,"y":0},"t":56.734,"s":[{"i":[[0,-16.133],[16.133,0],[0,16.133],[0,0],[0,0],[0,0],[16.133,0],[4.451,16.904]],"o":[[0,16.133],[-16.133,0],[0,0],[0,0],[0,0],[0,16.133],[-16.133,0],[-4.108,-15.602]],"v":[[-87.474,-53.404],[-116.936,-21.192],[-146.148,-53.404],[-133.805,-89.5],[132.629,-89.5],[145.723,-54.154],[117.011,-21.192],[86.049,-53.404]],"c":false}]},{"i":{"x":0.667,"y":1},"o":{"x":0.333,"y":0},"t":73,"s":[{"i":[[0,-16.133],[16.133,0],[0,16.133],[0,0],[0,0],[0,0],[16.133,0],[4.451,16.904]],"o":[[0,16.133],[-16.133,0],[0,0],[0,0],[0,0],[0,16.133],[-16.133,0],[-4.108,-15.602]],"v":[[-87.474,-53.404],[-116.936,-26.192],[-146.148,-53.404],[-133.805,-89.5],[132.629,-89.5],[145.723,-54.154],[117.011,-26.192],[86.049,-53.404]],"c":false}]},{"t":89,"s":[{"i":[[0,-16.133],[16.133,0],[0,16.133],[0,0],[0,0],[0,0],[16.133,0],[4.451,16.904]],"o":[[0,16.133],[-16.133,0],[0,0],[0,0],[0,0],[0,16.133],[-16.133,0],[-4.108,-15.602]],"v":[[-87.474,-53.404],[-116.936,-24.192],[-146.148,-53.404],[-133.805,-89.5],[132.629,-89.5],[145.723,-54.154],[117.011,-24.192],[86.049,-53.404]],"c":false}]}],"ix":2},"nm":"Path 1","mn":"ADBE Vector Shape - Group","hd":false},{"ty":"fl","c":{"a":0,"k":[0.922,0.902,0.937,1],"ix":4,"x":"var $bm_rt;\n$bm_rt = comp('wired-flat-3136-big-shop').layer('control').effect('primary')('Color');"},"o":{"a":0,"k":100,"ix":5},"r":1,"bm":0,"nm":".primary","mn":"ADBE Vector Graphic - Fill","hd":false,"cl":"primary"},{"ty":"tr","p":{"a":0,"k":[0,0],"ix":2},"a":{"a":0,"k":[0,0],"ix":1},"s":{"a":0,"k":[100,100],"ix":3},"r":{"a":0,"k":0,"ix":6},"o":{"a":0,"k":100,"ix":7},"sk":{"a":0,"k":0,"ix":4},"sa":{"a":0,"k":0,"ix":5},"nm":"Transform"}],"nm":"Group 4","np":3,"cix":2,"bm":0,"ix":4,"mn":"ADBE Vector Group","hd":false}],"ip":0,"op":300,"st":0,"ct":1,"bm":1},{"ddd":0,"ind":6,"ty":4,"nm":"Roof fill","parent":7,"sr":1,"ks":{"o":{"a":0,"k":100,"ix":11},"r":{"a":0,"k":0,"ix":10},"p":{"a":0,"k":[0,195.433,0],"ix":2,"l":2},"a":{"a":0,"k":[0,133.433,0],"ix":1,"l":2},"s":{"a":0,"k":[100,100,100],"ix":6,"l":2}},"ao":0,"shapes":[{"ty":"gr","it":[{"ind":0,"ty":"sh","ix":1,"ks":{"a":1,"k":[{"i":{"x":0.35,"y":1},"o":{"x":0.333,"y":0},"t":5,"s":[{"i":[[0,0],[0,0],[-16.133,0],[0,16.133],[0,0]],"o":[[0,0],[0,16.133],[16.133,0],[0,0],[0,0]],"v":[[-80.118,-90.25],[-87.474,-53.404],[-58.512,-24.942],[-29.3,-53.404],[-26.681,-90.5]],"c":false}]},{"i":{"x":0.667,"y":1},"o":{"x":0.65,"y":0},"t":16,"s":[{"i":[[0,0],[0,0],[-16.133,0],[0,16.133],[0,0]],"o":[[0,0],[0,21.404],[16.133,0],[0,0],[0,0]],"v":[[-80.118,-89.75],[-87.474,-53.404],[-58.448,-14.942],[-29.3,-53.404],[-26.681,-90]],"c":false}]},{"i":{"x":0.667,"y":1},"o":{"x":0.333,"y":0},"t":35,"s":[{"i":[[0,0],[0,0],[-16.133,0],[0,16.133],[0,0]],"o":[[0,0],[0,16.134],[16.133,0],[0,0],[0,0]],"v":[[-80.118,-89.75],[-87.474,-53.404],[-58.512,-31.941],[-29.3,-53.404],[-26.681,-90]],"c":false}]},{"i":{"x":0.667,"y":1},"o":{"x":0.333,"y":0},"t":52,"s":[{"i":[[0,0],[0,0],[-16.133,0],[0,16.133],[0,0]],"o":[[0,0],[0,16.133],[16.133,0],[0,0],[0,0]],"v":[[-80.118,-89.75],[-87.474,-53.404],[-58.512,-21.946],[-29.3,-53.404],[-26.681,-90]],"c":false}]},{"i":{"x":0.833,"y":1},"o":{"x":0.333,"y":0},"t":68,"s":[{"i":[[0,0],[0,0],[-16.133,0],[0,16.133],[0,0]],"o":[[0,0],[0,16.133],[16.133,0],[0,0],[0,0]],"v":[[-80.118,-89.75],[-87.474,-53.404],[-58.512,-26.942],[-29.3,-53.404],[-26.681,-90]],"c":false}]},{"t":84,"s":[{"i":[[0,0],[0,0],[-16.133,0],[0,16.133],[0,0]],"o":[[0,0],[0,16.133],[16.133,0],[0,0],[0,0]],"v":[[-80.118,-90.25],[-87.474,-53.404],[-58.512,-24.942],[-29.3,-53.404],[-26.681,-90.5]],"c":false}]}],"ix":2},"nm":"Path 1","mn":"ADBE Vector Shape - Group","hd":false},{"ty":"fl","c":{"a":0,"k":[0.573,0.078,0.047,1],"ix":4,"x":"var $bm_rt;\n$bm_rt = comp('wired-flat-3136-big-shop').layer('control').effect('quaternary')('Color');"},"o":{"a":0,"k":100,"ix":5},"r":1,"bm":0,"nm":".quaternary","mn":"ADBE Vector Graphic - Fill","hd":false,"cl":"quaternary"},{"ty":"tr","p":{"a":0,"k":[0,0],"ix":2},"a":{"a":0,"k":[0,0],"ix":1},"s":{"a":0,"k":[100,100],"ix":3},"r":{"a":0,"k":0,"ix":6},"o":{"a":0,"k":100,"ix":7},"sk":{"a":0,"k":0,"ix":4},"sa":{"a":0,"k":0,"ix":5},"nm":"Transform"}],"nm":"Group 1","np":3,"cix":2,"bm":0,"ix":1,"mn":"ADBE Vector Group","hd":false},{"ty":"gr","it":[{"ind":0,"ty":"sh","ix":1,"ks":{"a":1,"k":[{"i":{"x":0.35,"y":1},"o":{"x":0.333,"y":0},"t":5,"s":[{"i":[[0,0],[0,0],[-16.133,0],[0,16.133],[0,0]],"o":[[0,0],[0,16.133],[16.133,0],[0,0],[0,0]],"v":[[26.256,-90],[29.124,-53.404],[58.336,-24.692],[86.049,-53.404],[78.443,-90.25]],"c":false}]},{"i":{"x":0.667,"y":1},"o":{"x":0.65,"y":0},"t":16,"s":[{"i":[[0,0],[0,0],[-16.133,0],[0,16.133],[0,0]],"o":[[0,0],[0,16.133],[16.133,0],[0,0],[0,0]],"v":[[26.256,-89.5],[29.124,-53.404],[58.4,-14.692],[86.049,-53.404],[78.443,-89.75]],"c":false}]},{"i":{"x":0.667,"y":1},"o":{"x":0.333,"y":0},"t":35,"s":[{"i":[[0,0],[0,0],[-16.133,0],[0,16.133],[0,0]],"o":[[0,0],[0,16.133],[16.133,0],[0,0],[0,0]],"v":[[26.256,-89.5],[29.124,-53.404],[58.336,-31.691],[86.049,-53.404],[78.443,-89.75]],"c":false}]},{"i":{"x":0.667,"y":1},"o":{"x":0.333,"y":0},"t":52,"s":[{"i":[[0,0],[0,0],[-16.133,0],[0,16.133],[0,0]],"o":[[0,0],[0,16.133],[16.133,0],[0,0],[0,0]],"v":[[26.256,-89.5],[29.124,-53.404],[58.336,-21.696],[86.049,-53.404],[78.443,-89.75]],"c":false}]},{"i":{"x":0.833,"y":1},"o":{"x":0.333,"y":0},"t":68,"s":[{"i":[[0,0],[0,0],[-16.133,0],[0,16.133],[0,0]],"o":[[0,0],[0,16.133],[16.133,0],[0,0],[0,0]],"v":[[26.256,-89.5],[29.124,-53.404],[58.336,-26.692],[86.049,-53.404],[78.443,-89.75]],"c":false}]},{"t":84,"s":[{"i":[[0,0],[0,0],[-16.133,0],[0,16.133],[0,0]],"o":[[0,0],[0,16.133],[16.133,0],[0,0],[0,0]],"v":[[26.256,-90],[29.124,-53.404],[58.336,-24.692],[86.049,-53.404],[78.443,-90.25]],"c":false}]}],"ix":2},"nm":"Path 1","mn":"ADBE Vector Shape - Group","hd":false},{"ty":"fl","c":{"a":0,"k":[0.573,0.078,0.047,1],"ix":4,"x":"var $bm_rt;\n$bm_rt = comp('wired-flat-3136-big-shop').layer('control').effect('quaternary')('Color');"},"o":{"a":0,"k":100,"ix":5},"r":1,"bm":0,"nm":".quaternary","mn":"ADBE Vector Graphic - Fill","hd":false,"cl":"quaternary"},{"ty":"tr","p":{"a":0,"k":[0,0],"ix":2},"a":{"a":0,"k":[0,0],"ix":1},"s":{"a":0,"k":[100,100],"ix":3},"r":{"a":0,"k":0,"ix":6},"o":{"a":0,"k":100,"ix":7},"sk":{"a":0,"k":0,"ix":4},"sa":{"a":0,"k":0,"ix":5},"nm":"Transform"}],"nm":"Group 2","np":3,"cix":2,"bm":0,"ix":2,"mn":"ADBE Vector Group","hd":false},{"ty":"gr","it":[{"ind":0,"ty":"sh","ix":1,"ks":{"a":1,"k":[{"i":{"x":0.35,"y":1},"o":{"x":0.333,"y":0},"t":0,"s":[{"i":[[0,-16.133],[16.133,0],[0,16.133]],"o":[[0,16.133],[-16.133,0],[0,-16.133]],"v":[[29.124,-53.404],[-0.088,-24.192],[-29.3,-53.404]],"c":false}]},{"i":{"x":0.667,"y":1},"o":{"x":0.65,"y":0},"t":11,"s":[{"i":[[0,-16.133],[16.133,0],[0,16.133]],"o":[[0,16.133],[-16.133,0],[0,-16.133]],"v":[[29.124,-53.404],[-0.024,-14.192],[-29.3,-53.404]],"c":false}]},{"i":{"x":0.667,"y":1},"o":{"x":0.333,"y":0},"t":30.059,"s":[{"i":[[0,-16.133],[16.133,0],[0,16.133]],"o":[[0,16.133],[-16.133,0],[0,-16.133]],"v":[[29.124,-53.404],[-0.088,-31.192],[-29.3,-53.404]],"c":false}]},{"i":{"x":0.667,"y":1},"o":{"x":0.333,"y":0},"t":46.734,"s":[{"i":[[0,-16.133],[16.133,0],[0,16.133]],"o":[[0,16.133],[-16.133,0],[0,-16.133]],"v":[[29.124,-53.404],[-0.088,-21.192],[-29.3,-53.404]],"c":false}]},{"i":{"x":0.667,"y":1},"o":{"x":0.333,"y":0},"t":63,"s":[{"i":[[0,-16.133],[16.133,0],[0,16.133]],"o":[[0,16.133],[-16.133,0],[0,-16.133]],"v":[[29.124,-53.404],[-0.088,-26.192],[-29.3,-53.404]],"c":false}]},{"t":79,"s":[{"i":[[0,-16.133],[16.133,0],[0,16.133]],"o":[[0,16.133],[-16.133,0],[0,-16.133]],"v":[[29.124,-53.404],[-0.088,-24.192],[-29.3,-53.404]],"c":false}]}],"ix":2},"nm":"Path 1","mn":"ADBE Vector Shape - Group","hd":false},{"ty":"fl","c":{"a":0,"k":[0.922,0.902,0.937,1],"ix":4,"x":"var $bm_rt;\n$bm_rt = comp('wired-flat-3136-big-shop').layer('control').effect('primary')('Color');"},"o":{"a":0,"k":100,"ix":5},"r":1,"bm":0,"nm":".primary","mn":"ADBE Vector Graphic - Fill","hd":false,"cl":"primary"},{"ty":"tr","p":{"a":0,"k":[0,0],"ix":2},"a":{"a":0,"k":[0,0],"ix":1},"s":{"a":0,"k":[100,100],"ix":3},"r":{"a":0,"k":0,"ix":6},"o":{"a":0,"k":100,"ix":7},"sk":{"a":0,"k":0,"ix":4},"sa":{"a":0,"k":0,"ix":5},"nm":"Transform"}],"nm":"Group 3","np":3,"cix":2,"bm":0,"ix":3,"mn":"ADBE Vector Group","hd":false},{"ty":"gr","it":[{"ind":0,"ty":"sh","ix":1,"ks":{"a":1,"k":[{"i":{"x":0.35,"y":1},"o":{"x":0.333,"y":0},"t":10,"s":[{"i":[[0,-16.133],[16.133,0],[0,16.133],[0,0],[0,0],[0,0],[16.133,0],[4.451,16.904]],"o":[[0,16.133],[-16.133,0],[0,0],[0,0],[0,0],[0,16.133],[-16.133,0],[-4.108,-15.602]],"v":[[-87.474,-53.404],[-116.936,-24.192],[-146.148,-53.404],[-133.805,-89.5],[132.629,-89.5],[145.723,-54.154],[117.011,-24.192],[86.049,-53.404]],"c":false}]},{"i":{"x":0.667,"y":1},"o":{"x":0.65,"y":0},"t":21,"s":[{"i":[[0,-16.133],[16.133,0],[0,22.404],[0,0],[0,0],[0,0],[16.133,0],[4.451,16.904]],"o":[[0,16.133],[-16.133,0],[0,0],[0,0],[0,0],[0,22.154],[-16.133,0],[-4.108,-15.602]],"v":[[-87.474,-53.404],[-116.873,-14.192],[-146.148,-53.404],[-133.805,-89.5],[132.629,-89.5],[145.723,-54.154],[117.074,-14.192],[86.049,-53.404]],"c":false}]},{"i":{"x":0.667,"y":1},"o":{"x":0.333,"y":0},"t":40.059,"s":[{"i":[[0,-16.133],[16.133,0],[0,16.133],[0,0],[0,0],[0,0],[16.133,0],[4.451,16.904]],"o":[[0,16.133],[-16.133,0],[0,0],[0,0],[0,0],[0,16.133],[-16.133,0],[-4.108,-15.602]],"v":[[-87.474,-53.404],[-116.936,-31.192],[-146.148,-53.404],[-133.805,-89.5],[132.629,-89.5],[145.723,-54.154],[117.011,-31.192],[86.049,-53.404]],"c":false}]},{"i":{"x":0.667,"y":1},"o":{"x":0.333,"y":0},"t":56.734,"s":[{"i":[[0,-16.133],[16.133,0],[0,16.133],[0,0],[0,0],[0,0],[16.133,0],[4.451,16.904]],"o":[[0,16.133],[-16.133,0],[0,0],[0,0],[0,0],[0,16.133],[-16.133,0],[-4.108,-15.602]],"v":[[-87.474,-53.404],[-116.936,-21.192],[-146.148,-53.404],[-133.805,-89.5],[132.629,-89.5],[145.723,-54.154],[117.011,-21.192],[86.049,-53.404]],"c":false}]},{"i":{"x":0.667,"y":1},"o":{"x":0.333,"y":0},"t":73,"s":[{"i":[[0,-16.133],[16.133,0],[0,16.133],[0,0],[0,0],[0,0],[16.133,0],[4.451,16.904]],"o":[[0,16.133],[-16.133,0],[0,0],[0,0],[0,0],[0,16.133],[-16.133,0],[-4.108,-15.602]],"v":[[-87.474,-53.404],[-116.936,-26.192],[-146.148,-53.404],[-133.805,-89.5],[132.629,-89.5],[145.723,-54.154],[117.011,-26.192],[86.049,-53.404]],"c":false}]},{"t":89,"s":[{"i":[[0,-16.133],[16.133,0],[0,16.133],[0,0],[0,0],[0,0],[16.133,0],[4.451,16.904]],"o":[[0,16.133],[-16.133,0],[0,0],[0,0],[0,0],[0,16.133],[-16.133,0],[-4.108,-15.602]],"v":[[-87.474,-53.404],[-116.936,-24.192],[-146.148,-53.404],[-133.805,-89.5],[132.629,-89.5],[145.723,-54.154],[117.011,-24.192],[86.049,-53.404]],"c":false}]}],"ix":2},"nm":"Path 1","mn":"ADBE Vector Shape - Group","hd":false},{"ty":"fl","c":{"a":0,"k":[0.922,0.902,0.937,1],"ix":4,"x":"var $bm_rt;\n$bm_rt = comp('wired-flat-3136-big-shop').layer('control').effect('primary')('Color');"},"o":{"a":0,"k":100,"ix":5},"r":1,"bm":0,"nm":".primary","mn":"ADBE Vector Graphic - Fill","hd":false,"cl":"primary"},{"ty":"tr","p":{"a":0,"k":[0,0],"ix":2},"a":{"a":0,"k":[0,0],"ix":1},"s":{"a":0,"k":[100,100],"ix":3},"r":{"a":0,"k":0,"ix":6},"o":{"a":0,"k":100,"ix":7},"sk":{"a":0,"k":0,"ix":4},"sa":{"a":0,"k":0,"ix":5},"nm":"Transform"}],"nm":"Group 4","np":3,"cix":2,"bm":0,"ix":4,"mn":"ADBE Vector Group","hd":false}],"ip":0,"op":300,"st":0,"ct":1,"bm":0},{"ddd":0,"ind":7,"ty":3,"nm":"Bottom 2","sr":1,"ks":{"o":{"a":0,"k":100,"ix":11},"r":{"a":0,"k":0,"ix":10},"p":{"a":0,"k":[215,375.433,0],"ix":2,"l":2},"a":{"a":0,"k":[0,133.433,0],"ix":1,"l":2},"s":{"a":0,"k":[100,100,100],"ix":6,"l":2}},"ao":0,"ip":0,"op":300,"st":0,"ct":1,"bm":0},{"ddd":0,"ind":8,"ty":4,"nm":"mask","td":1,"sr":1,"ks":{"o":{"a":0,"k":100,"ix":11},"r":{"a":0,"k":0,"ix":10},"p":{"a":0,"k":[215,339.5,0],"ix":2,"l":2},"a":{"a":0,"k":[0,0,0],"ix":1,"l":2},"s":{"a":0,"k":[100,100,100],"ix":6,"l":2}},"ao":0,"shapes":[{"ty":"gr","it":[{"ind":0,"ty":"sh","ix":1,"ks":{"a":0,"k":{"i":[[0,0],[0,0],[1.657,0],[0,0],[0,-1.657],[0,0]],"o":[[0,0],[0,-1.657],[0,0],[-1.657,0],[0,0],[0,0]],"v":[[37,36.5],[37,-33.5],[34,-36.5],[-34,-36.5],[-37,-33.5],[-37,36.5]],"c":false},"ix":2},"nm":"Path 1","mn":"ADBE Vector Shape - Group","hd":false},{"ind":1,"ty":"sh","ix":2,"ks":{"a":0,"k":{"i":[[0,0],[0,0]],"o":[[0,0],[0,0]],"v":[[37,36.5],[-37,36.5]],"c":false},"ix":2},"nm":"Path 2","mn":"ADBE Vector Shape - Group","hd":false},{"ty":"mm","mm":1,"nm":"Merge Paths 1","mn":"ADBE Vector Filter - Merge","hd":false},{"ty":"fl","c":{"a":0,"k":[0.921568632126,0.901960790157,0.937254905701,1],"ix":4},"o":{"a":0,"k":50,"ix":5},"r":1,"bm":1,"nm":"Fill 1","mn":"ADBE Vector Graphic - Fill","hd":false},{"ty":"fl","c":{"a":0,"k":[0.921568632126,0.901960790157,0.937254905701,1],"ix":4},"o":{"a":0,"k":100,"ix":5},"r":1,"bm":0,"nm":"Fill 2","mn":"ADBE Vector Graphic - Fill","hd":false},{"ty":"tr","p":{"a":0,"k":[0,0],"ix":2},"a":{"a":0,"k":[0,0],"ix":1},"s":{"a":0,"k":[100,100],"ix":3},"r":{"a":0,"k":0,"ix":6},"o":{"a":0,"k":100,"ix":7},"sk":{"a":0,"k":0,"ix":4},"sa":{"a":0,"k":0,"ix":5},"nm":"Transform"}],"nm":"Vector","np":5,"cix":2,"bm":0,"ix":1,"mn":"ADBE Vector Group","hd":false}],"ip":0,"op":300,"st":0,"ct":1,"bm":0},{"ddd":0,"ind":9,"ty":4,"nm":"Vector (Stroke)","parent":10,"tt":1,"tp":8,"sr":1,"ks":{"o":{"a":0,"k":100,"ix":11},"r":{"a":0,"k":0,"ix":10},"p":{"a":1,"k":[{"i":{"x":0.667,"y":1},"o":{"x":0.333,"y":0},"t":0,"s":[14.413,0,0],"to":[0,0,0],"ti":[0,0,0]},{"i":{"x":0.667,"y":0.667},"o":{"x":0.333,"y":0.333},"t":30,"s":[9.413,0,0],"to":[0,0,0],"ti":[0,0,0]},{"i":{"x":0.667,"y":1},"o":{"x":0.333,"y":0},"t":60,"s":[9.413,0,0],"to":[0,0,0],"ti":[0,0,0]},{"t":90,"s":[14.413,0,0]}],"ix":2,"l":2},"a":{"a":0,"k":[0,0,0],"ix":1,"l":2},"s":{"a":0,"k":[100,100,100],"ix":6,"l":2}},"ao":0,"shapes":[{"ty":"gr","it":[{"ind":0,"ty":"sh","ix":1,"ks":{"a":0,"k":{"i":[[0,0],[0,-2.761],[-2.759,0],[0,0],[0,2.761],[2.759,0]],"o":[[-2.759,0],[0,2.761],[0,0],[2.759,0],[0,-2.761],[0,0]],"v":[[-0.005,-5],[-5,0],[-0.005,5],[0.005,5],[5,0],[0.005,-5]],"c":true},"ix":2},"nm":"Path 1","mn":"ADBE Vector Shape - Group","hd":false},{"ty":"fl","c":{"a":0,"k":[0.227,0.2,0.278,1],"ix":4,"x":"var $bm_rt;\n$bm_rt = comp('wired-flat-3136-big-shop').layer('control').effect('secondary')('Color');"},"o":{"a":0,"k":100,"ix":5},"r":1,"bm":0,"nm":".secondary","mn":"ADBE Vector Graphic - Fill","hd":false,"cl":"secondary"},{"ty":"tr","p":{"a":0,"k":[0,0],"ix":2},"a":{"a":0,"k":[0,0],"ix":1},"s":{"a":0,"k":[100,100],"ix":3},"r":{"a":0,"k":0,"ix":6},"o":{"a":0,"k":100,"ix":7},"sk":{"a":0,"k":0,"ix":4},"sa":{"a":0,"k":0,"ix":5},"nm":"Transform"}],"nm":"Vector (Stroke)","np":2,"cix":2,"bm":0,"ix":1,"mn":"ADBE Vector Group","hd":false}],"ip":0,"op":300,"st":0,"ct":1,"bm":0},{"ddd":0,"ind":10,"ty":3,"nm":"door R","parent":7,"sr":1,"ks":{"o":{"a":0,"k":100,"ix":11},"r":{"a":0,"k":0,"ix":10},"p":{"a":1,"k":[{"i":{"x":0.41,"y":1},"o":{"x":0.59,"y":0},"t":0,"s":[0,97.5,0],"to":[0,0,0],"ti":[0,0,0]},{"i":{"x":0.41,"y":0.41},"o":{"x":0.59,"y":0.59},"t":30,"s":[20,97.5,0],"to":[0,0,0],"ti":[0,0,0]},{"i":{"x":0.41,"y":1},"o":{"x":0.59,"y":0},"t":60,"s":[20,97.5,0],"to":[0,0,0],"ti":[0,0,0]},{"t":90,"s":[0,97.5,0]}],"ix":2,"l":2},"a":{"a":0,"k":[0,0,0],"ix":1,"l":2},"s":{"a":0,"k":[100,100,100],"ix":6,"l":2}},"ao":0,"ip":0,"op":1799,"st":-1,"ct":1,"bm":0},{"ddd":0,"ind":11,"ty":4,"nm":"door fill","sr":1,"ks":{"o":{"a":0,"k":100,"ix":11},"r":{"a":0,"k":0,"ix":10},"p":{"a":0,"k":[215,339.5,0],"ix":2,"l":2},"a":{"a":0,"k":[0,0,0],"ix":1,"l":2},"s":{"a":0,"k":[100,100,100],"ix":6,"l":2}},"ao":0,"shapes":[{"ty":"gr","it":[{"ind":0,"ty":"sh","ix":1,"ks":{"a":1,"k":[{"i":{"x":0.489,"y":1},"o":{"x":0.556,"y":0},"t":0,"s":[{"i":[[0,0],[0,0],[1.657,0],[0,0],[0,-1.657],[0,0]],"o":[[0,0],[0,-1.657],[0,0],[-1.657,0],[0,0],[0,0]],"v":[[37,36.5],[37,-33.5],[34,-36.5],[3.25,-36.5],[0.25,-33.5],[0.25,36.5]],"c":false}]},{"i":{"x":0.667,"y":1},"o":{"x":0.333,"y":0},"t":30,"s":[{"i":[[0,0],[0,0],[1.657,0],[0,0],[0,-1.657],[0,0]],"o":[[0,0],[0,-1.657],[0,0],[-1.657,0],[0,0],[0,0]],"v":[[37,36.5],[37,-33.5],[34,-36.5],[23.25,-36.5],[20.25,-33.5],[20.25,36.5]],"c":false}]},{"i":{"x":0.496,"y":1},"o":{"x":0.539,"y":0},"t":60,"s":[{"i":[[0,0],[0,0],[1.657,0],[0,0],[0,-1.657],[0,0]],"o":[[0,0],[0,-1.657],[0,0],[-1.657,0],[0,0],[0,0]],"v":[[37,36.5],[37,-33.5],[34,-36.5],[23.25,-36.5],[20.25,-33.5],[20.25,36.5]],"c":false}]},{"t":90,"s":[{"i":[[0,0],[0,0],[1.657,0],[0,0],[0,-1.657],[0,0]],"o":[[0,0],[0,-1.657],[0,0],[-1.657,0],[0,0],[0,0]],"v":[[37,36.5],[37,-33.5],[34,-36.5],[3.25,-36.5],[0.25,-33.5],[0.25,36.5]],"c":false}]}],"ix":2},"nm":"Path 1","mn":"ADBE Vector Shape - Group","hd":false},{"ty":"mm","mm":1,"nm":"Merge Paths 1","mn":"ADBE Vector Filter - Merge","hd":false},{"ty":"fl","c":{"a":0,"k":[0.922,0.902,0.937,1],"ix":4,"x":"var $bm_rt;\n$bm_rt = comp('wired-flat-3136-big-shop').layer('control').effect('primary')('Color');"},"o":{"a":0,"k":100,"ix":5},"r":1,"bm":0,"nm":".primary","mn":"ADBE Vector Graphic - Fill","hd":false,"cl":"primary"},{"ty":"tr","p":{"a":0,"k":[0,0],"ix":2},"a":{"a":0,"k":[0,0],"ix":1},"s":{"a":0,"k":[100,100],"ix":3},"r":{"a":0,"k":0,"ix":6},"o":{"a":0,"k":100,"ix":7},"sk":{"a":0,"k":0,"ix":4},"sa":{"a":0,"k":0,"ix":5},"nm":"Transform"}],"nm":"Vector","np":3,"cix":2,"bm":0,"ix":1,"mn":"ADBE Vector Group","hd":false}],"ip":0,"op":300,"st":0,"ct":1,"bm":0},{"ddd":0,"ind":12,"ty":4,"nm":"mask 2","td":1,"sr":1,"ks":{"o":{"a":0,"k":100,"ix":11},"r":{"a":0,"k":0,"ix":10},"p":{"a":0,"k":[215,339.5,0],"ix":2,"l":2},"a":{"a":0,"k":[0,0,0],"ix":1,"l":2},"s":{"a":0,"k":[100,100,100],"ix":6,"l":2}},"ao":0,"shapes":[{"ty":"gr","it":[{"ind":0,"ty":"sh","ix":1,"ks":{"a":0,"k":{"i":[[0,0],[0,0],[1.657,0],[0,0],[0,-1.657],[0,0]],"o":[[0,0],[0,-1.657],[0,0],[-1.657,0],[0,0],[0,0]],"v":[[37,36.5],[37,-33.5],[34,-36.5],[-34,-36.5],[-37,-33.5],[-37,36.5]],"c":false},"ix":2},"nm":"Path 1","mn":"ADBE Vector Shape - Group","hd":false},{"ind":1,"ty":"sh","ix":2,"ks":{"a":0,"k":{"i":[[0,0],[0,0]],"o":[[0,0],[0,0]],"v":[[37,36.5],[-37,36.5]],"c":false},"ix":2},"nm":"Path 2","mn":"ADBE Vector Shape - Group","hd":false},{"ty":"mm","mm":1,"nm":"Merge Paths 1","mn":"ADBE Vector Filter - Merge","hd":false},{"ty":"fl","c":{"a":0,"k":[0.921568632126,0.901960790157,0.937254905701,1],"ix":4},"o":{"a":0,"k":50,"ix":5},"r":1,"bm":1,"nm":"Fill 1","mn":"ADBE Vector Graphic - Fill","hd":false},{"ty":"fl","c":{"a":0,"k":[0.921568632126,0.901960790157,0.937254905701,1],"ix":4},"o":{"a":0,"k":100,"ix":5},"r":1,"bm":0,"nm":"Fill 2","mn":"ADBE Vector Graphic - Fill","hd":false},{"ty":"tr","p":{"a":0,"k":[0,0],"ix":2},"a":{"a":0,"k":[0,0],"ix":1},"s":{"a":0,"k":[100,100],"ix":3},"r":{"a":0,"k":0,"ix":6},"o":{"a":0,"k":100,"ix":7},"sk":{"a":0,"k":0,"ix":4},"sa":{"a":0,"k":0,"ix":5},"nm":"Transform"}],"nm":"Vector","np":5,"cix":2,"bm":0,"ix":1,"mn":"ADBE Vector Group","hd":false}],"ip":0,"op":300,"st":0,"ct":1,"bm":0},{"ddd":0,"ind":13,"ty":4,"nm":"Vector (Stroke) 2","parent":14,"tt":1,"tp":12,"sr":1,"ks":{"o":{"a":0,"k":100,"ix":11},"r":{"a":0,"k":0,"ix":10},"p":{"a":1,"k":[{"i":{"x":0.667,"y":1},"o":{"x":0.333,"y":0},"t":0,"s":[-15.587,0,0],"to":[0,0,0],"ti":[0,0,0]},{"i":{"x":0.667,"y":0.667},"o":{"x":0.333,"y":0.333},"t":30,"s":[-10.587,0,0],"to":[0,0,0],"ti":[0,0,0]},{"i":{"x":0.667,"y":1},"o":{"x":0.333,"y":0},"t":60,"s":[-10.587,0,0],"to":[0,0,0],"ti":[0,0,0]},{"t":90,"s":[-15.587,0,0]}],"ix":2,"l":2},"a":{"a":0,"k":[0,0,0],"ix":1,"l":2},"s":{"a":0,"k":[100,100,100],"ix":6,"l":2}},"ao":0,"shapes":[{"ty":"gr","it":[{"ind":0,"ty":"sh","ix":1,"ks":{"a":0,"k":{"i":[[0,0],[0,-2.761],[-2.759,0],[0,0],[0,2.761],[2.759,0]],"o":[[-2.759,0],[0,2.761],[0,0],[2.759,0],[0,-2.761],[0,0]],"v":[[-0.005,-5],[-5,0],[-0.005,5],[0.005,5],[5,0],[0.005,-5]],"c":true},"ix":2},"nm":"Path 1","mn":"ADBE Vector Shape - Group","hd":false},{"ty":"fl","c":{"a":0,"k":[0.227,0.2,0.278,1],"ix":4,"x":"var $bm_rt;\n$bm_rt = comp('wired-flat-3136-big-shop').layer('control').effect('secondary')('Color');"},"o":{"a":0,"k":100,"ix":5},"r":1,"bm":0,"nm":".secondary","mn":"ADBE Vector Graphic - Fill","hd":false,"cl":"secondary"},{"ty":"tr","p":{"a":0,"k":[0,0],"ix":2},"a":{"a":0,"k":[0,0],"ix":1},"s":{"a":0,"k":[100,100],"ix":3},"r":{"a":0,"k":0,"ix":6},"o":{"a":0,"k":100,"ix":7},"sk":{"a":0,"k":0,"ix":4},"sa":{"a":0,"k":0,"ix":5},"nm":"Transform"}],"nm":"Vector (Stroke)","np":2,"cix":2,"bm":0,"ix":1,"mn":"ADBE Vector Group","hd":false}],"ip":0,"op":300,"st":0,"ct":1,"bm":0},{"ddd":0,"ind":14,"ty":3,"nm":"door L","parent":7,"sr":1,"ks":{"o":{"a":0,"k":100,"ix":11},"r":{"a":0,"k":0,"ix":10},"p":{"a":1,"k":[{"i":{"x":0.41,"y":1},"o":{"x":0.59,"y":0},"t":0,"s":[0,97.5,0],"to":[0,0,0],"ti":[0,0,0]},{"i":{"x":0.41,"y":0.41},"o":{"x":0.59,"y":0.59},"t":30,"s":[-20,97.5,0],"to":[0,0,0],"ti":[0,0,0]},{"i":{"x":0.41,"y":1},"o":{"x":0.59,"y":0},"t":60,"s":[-20,97.5,0],"to":[0,0,0],"ti":[0,0,0]},{"t":90,"s":[0,97.5,0]}],"ix":2,"l":2},"a":{"a":0,"k":[0,0,0],"ix":1,"l":2},"s":{"a":0,"k":[100,100,100],"ix":6,"l":2}},"ao":0,"ip":1,"op":89,"st":-1,"ct":1,"bm":0},{"ddd":0,"ind":15,"ty":4,"nm":"door fill 2","sr":1,"ks":{"o":{"a":0,"k":100,"ix":11},"r":{"a":0,"k":0,"ix":10},"p":{"a":0,"k":[215,339.5,0],"ix":2,"l":2},"a":{"a":0,"k":[0,0,0],"ix":1,"l":2},"s":{"a":0,"k":[100,100,100],"ix":6,"l":2}},"ao":0,"shapes":[{"ty":"gr","it":[{"ind":0,"ty":"sh","ix":1,"ks":{"a":1,"k":[{"i":{"x":0.501,"y":1},"o":{"x":0.473,"y":0},"t":0,"s":[{"i":[[0,0],[0,0],[1.657,0],[0,0],[0,-1.657],[0,0]],"o":[[0,0],[0,-1.657],[0,0],[-1.657,0],[0,0],[0,0]],"v":[[0.25,36.5],[0.25,-33.5],[-2.75,-36.5],[-34,-36.5],[-37,-33.5],[-37,36.5]],"c":false}]},{"i":{"x":0.667,"y":1},"o":{"x":0.333,"y":0},"t":30,"s":[{"i":[[0,0],[0,0],[1.657,0],[0,0],[0,-1.657],[0,0]],"o":[[0,0],[0,-1.657],[0,0],[-1.657,0],[0,0],[0,0]],"v":[[-19.75,36.5],[-19.75,-33.5],[-22.75,-36.5],[-34,-36.5],[-37,-33.5],[-37,36.5]],"c":false}]},{"i":{"x":0.449,"y":1},"o":{"x":0.539,"y":0},"t":60,"s":[{"i":[[0,0],[0,0],[1.657,0],[0,0],[0,-1.657],[0,0]],"o":[[0,0],[0,-1.657],[0,0],[-1.657,0],[0,0],[0,0]],"v":[[-19.75,36.5],[-19.75,-33.5],[-22.75,-36.5],[-34,-36.5],[-37,-33.5],[-37,36.5]],"c":false}]},{"t":90,"s":[{"i":[[0,0],[0,0],[1.657,0],[0,0],[0,-1.657],[0,0]],"o":[[0,0],[0,-1.657],[0,0],[-1.657,0],[0,0],[0,0]],"v":[[0.25,36.5],[0.25,-33.5],[-2.75,-36.5],[-34,-36.5],[-37,-33.5],[-37,36.5]],"c":false}]}],"ix":2},"nm":"Path 1","mn":"ADBE Vector Shape - Group","hd":false},{"ty":"mm","mm":1,"nm":"Merge Paths 1","mn":"ADBE Vector Filter - Merge","hd":false},{"ty":"fl","c":{"a":0,"k":[0.922,0.902,0.937,1],"ix":4,"x":"var $bm_rt;\n$bm_rt = comp('wired-flat-3136-big-shop').layer('control').effect('primary')('Color');"},"o":{"a":0,"k":100,"ix":5},"r":1,"bm":0,"nm":".primary","mn":"ADBE Vector Graphic - Fill","hd":false,"cl":"primary"},{"ty":"tr","p":{"a":0,"k":[0,0],"ix":2},"a":{"a":0,"k":[0,0],"ix":1},"s":{"a":0,"k":[100,100],"ix":3},"r":{"a":0,"k":0,"ix":6},"o":{"a":0,"k":100,"ix":7},"sk":{"a":0,"k":0,"ix":4},"sa":{"a":0,"k":0,"ix":5},"nm":"Transform"}],"nm":"Vector","np":3,"cix":2,"bm":0,"ix":1,"mn":"ADBE Vector Group","hd":false}],"ip":0,"op":300,"st":0,"ct":1,"bm":0},{"ddd":0,"ind":16,"ty":4,"nm":"Rectangle 95","sr":1,"ks":{"o":{"a":0,"k":100,"ix":11},"r":{"a":0,"k":0,"ix":10},"p":{"a":0,"k":[124,341.625,0],"ix":2,"l":2},"a":{"a":0,"k":[0,0,0],"ix":1,"l":2},"s":{"a":0,"k":[100,100,100],"ix":6,"l":2}},"ao":0,"shapes":[{"ty":"gr","it":[{"ind":0,"ty":"sh","ix":1,"ks":{"a":0,"k":{"i":[[0,0],[0,0],[0,0],[-1.657,0],[0,0],[0,1.657]],"o":[[0,0],[0,0],[0,1.657],[0,0],[1.657,0],[0,0]],"v":[[15,-3.5],[-15,-3.5],[-15,0.5],[-12,3.5],[12,3.5],[15,0.5]],"c":true},"ix":2},"nm":"Path 1","mn":"ADBE Vector Shape - Group","hd":false},{"ty":"fl","c":{"a":0,"k":[0.227,0.2,0.278,1],"ix":4,"x":"var $bm_rt;\n$bm_rt = comp('wired-flat-3136-big-shop').layer('control').effect('secondary')('Color');"},"o":{"a":0,"k":100,"ix":5},"r":1,"bm":0,"nm":".secondary","mn":"ADBE Vector Graphic - Fill","hd":false,"cl":"secondary"},{"ty":"tr","p":{"a":0,"k":[0,0],"ix":2},"a":{"a":0,"k":[0,0],"ix":1},"s":{"a":0,"k":[100,100],"ix":3},"r":{"a":0,"k":0,"ix":6},"o":{"a":0,"k":100,"ix":7},"sk":{"a":0,"k":0,"ix":4},"sa":{"a":0,"k":0,"ix":5},"nm":"Transform"}],"nm":"Rectangle 94","np":2,"cix":2,"bm":0,"ix":1,"mn":"ADBE Vector Group","hd":false}],"ip":0,"op":300,"st":0,"ct":1,"bm":0},{"ddd":0,"ind":17,"ty":4,"nm":"Intersect 8","sr":1,"ks":{"o":{"a":0,"k":30,"ix":11},"r":{"a":0,"k":0,"ix":10},"p":{"a":0,"k":[124,324,0],"ix":2,"l":2},"a":{"a":0,"k":[0,0,0],"ix":1,"l":2},"s":{"a":0,"k":[100,100,100],"ix":6,"l":2}},"ao":0,"shapes":[{"ty":"gr","it":[{"ind":0,"ty":"sh","ix":1,"ks":{"a":0,"k":{"i":[[0,0],[0,0],[0,-1.657],[0,0]],"o":[[0,0],[1.657,0],[0,0],[0,0]],"v":[[-9.5,-21],[12,-21],[15,-18],[15,3.5]],"c":true},"ix":2},"nm":"Path 1","mn":"ADBE Vector Shape - Group","hd":false},{"ind":1,"ty":"sh","ix":2,"ks":{"a":0,"k":{"i":[[0,0],[0,0],[0.01,1.648],[0,0]],"o":[[0,0],[-1.65,0],[0,0],[0,0]],"v":[[10.811,21],[-12,21],[-15,18.019],[-15,-4.81]],"c":true},"ix":2},"nm":"Path 2","mn":"ADBE Vector Shape - Group","hd":false},{"ty":"mm","mm":1,"nm":"Merge Paths 1","mn":"ADBE Vector Filter - Merge","hd":false},{"ty":"fl","c":{"a":0,"k":[0.922,0.902,0.937,1],"ix":4,"x":"var $bm_rt;\n$bm_rt = comp('wired-flat-3136-big-shop').layer('control').effect('primary')('Color');"},"o":{"a":0,"k":100,"ix":5},"r":1,"bm":0,"nm":".primary","mn":"ADBE Vector Graphic - Fill","hd":false,"cl":"primary"},{"ty":"tr","p":{"a":0,"k":[0,0],"ix":2},"a":{"a":0,"k":[0,0],"ix":1},"s":{"a":0,"k":[100,100],"ix":3},"r":{"a":0,"k":0,"ix":6},"o":{"a":0,"k":100,"ix":7},"sk":{"a":0,"k":0,"ix":4},"sa":{"a":0,"k":0,"ix":5},"nm":"Transform"}],"nm":"Intersect","np":4,"cix":2,"bm":0,"ix":1,"mn":"ADBE Vector Group","hd":false}],"ip":0,"op":300,"st":0,"ct":1,"bm":0},{"ddd":0,"ind":18,"ty":4,"nm":"Intersect 7","sr":1,"ks":{"o":{"a":0,"k":30,"ix":11},"r":{"a":0,"k":0,"ix":10},"p":{"a":0,"k":[215,146,0],"ix":2,"l":2},"a":{"a":0,"k":[0,0,0],"ix":1,"l":2},"s":{"a":0,"k":[100,100,100],"ix":6,"l":2}},"ao":0,"shapes":[{"ty":"gr","it":[{"ind":0,"ty":"sh","ix":1,"ks":{"a":0,"k":{"i":[[0,0],[1.657,0],[0,0],[0,1.657],[0,0],[-1.657,0],[0,0],[0,0]],"o":[[0,1.657],[0,0],[-1.657,0],[0,0],[0,-1.657],[0,0],[0,0],[0,0]],"v":[[-76,18],[-79,21],[-103,21],[-106,18],[-106,-18],[-103,-21],[-94.633,-21],[-76,-2.367]],"c":true},"ix":2},"nm":"Path 1","mn":"ADBE Vector Shape - Group","hd":false},{"ind":1,"ty":"sh","ix":2,"ks":{"a":0,"k":{"i":[[0,0],[1.657,0],[0,0],[0,0],[0,0],[-1.088,0.451],[0,0]],"o":[[0,1.657],[0,0],[0,0],[0,0],[0,-1.251],[0,0],[0,0]],"v":[[-15,18],[-18,21],[-30.943,21],[-45,6.943],[-45,-18],[-43.147,-20.773],[-15,7.382]],"c":true},"ix":2},"nm":"Path 2","mn":"ADBE Vector Shape - Group","hd":false},{"ind":2,"ty":"sh","ix":3,"ks":{"a":0,"k":{"i":[[0,0],[0,0],[0,0],[-1.657,0],[0,0],[0,-1.657],[0,0],[1.635,-0.025]],"o":[[0,0],[0,0],[0,-1.657],[0,0],[1.657,0],[0,0],[0,1.641],[0,0]],"v":[[42.795,21],[16,-5.795],[16,-18],[19,-21],[43,-21],[46,-18],[46,18],[43.046,21]],"c":true},"ix":2},"nm":"Path 3","mn":"ADBE Vector Shape - Group","hd":false},{"ind":3,"ty":"sh","ix":4,"ks":{"a":0,"k":{"i":[[0,-1.657],[0,0],[0,0],[-0.718,0],[0,0]],"o":[[0,0],[0,0],[0.516,-0.42],[0,0],[1.657,0]],"v":[[106,-18],[106,8.565],[77.107,-20.328],[79,-21],[103,-21]],"c":true},"ix":2},"nm":"Path 4","mn":"ADBE Vector Shape - Group","hd":false},{"ind":4,"ty":"sh","ix":5,"ks":{"a":0,"k":{"i":[[0,0],[0,0],[0,0],[-1.635,-0.025]],"o":[[0,0],[0,0],[0,1.641],[0,0]],"v":[[96.745,21],[76,0.255],[76,18],[78.954,21]],"c":true},"ix":2},"nm":"Path 5","mn":"ADBE Vector Shape - Group","hd":false},{"ty":"mm","mm":1,"nm":"Merge Paths 1","mn":"ADBE Vector Filter - Merge","hd":false},{"ty":"fl","c":{"a":0,"k":[0.922,0.902,0.937,1],"ix":4,"x":"var $bm_rt;\n$bm_rt = comp('wired-flat-3136-big-shop').layer('control').effect('primary')('Color');"},"o":{"a":0,"k":100,"ix":5},"r":1,"bm":0,"nm":".primary","mn":"ADBE Vector Graphic - Fill","hd":false,"cl":"primary"},{"ty":"tr","p":{"a":0,"k":[0,0],"ix":2},"a":{"a":0,"k":[0,0],"ix":1},"s":{"a":0,"k":[100,100],"ix":3},"r":{"a":0,"k":0,"ix":6},"o":{"a":0,"k":100,"ix":7},"sk":{"a":0,"k":0,"ix":4},"sa":{"a":0,"k":0,"ix":5},"nm":"Transform"}],"nm":"Intersect","np":7,"cix":2,"bm":0,"ix":1,"mn":"ADBE Vector Group","hd":false}],"ip":0,"op":300,"st":0,"ct":1,"bm":0},{"ddd":0,"ind":19,"ty":4,"nm":"Vector 14","sr":1,"ks":{"o":{"a":0,"k":100,"ix":11},"r":{"a":0,"k":0,"ix":10},"p":{"a":0,"k":[215,146,0],"ix":2,"l":2},"a":{"a":0,"k":[0,0,0],"ix":1,"l":2},"s":{"a":0,"k":[100,100,100],"ix":6,"l":2}},"ao":0,"shapes":[{"ty":"gr","it":[{"ind":0,"ty":"sh","ix":1,"ks":{"a":0,"k":{"i":[[0,0],[0,1.657],[0,0],[1.657,0],[0,0],[0,-1.657],[0,0],[-1.657,0]],"o":[[1.657,0],[0,0],[0,-1.657],[0,0],[-1.657,0],[0,0],[0,1.657],[0,0]],"v":[[-79,21],[-76,18],[-76,-18],[-79,-21],[-103,-21],[-106,-18],[-106,18],[-103,21]],"c":true},"ix":2},"nm":"Path 1","mn":"ADBE Vector Shape - Group","hd":false},{"ind":1,"ty":"sh","ix":2,"ks":{"a":0,"k":{"i":[[0,0],[0,1.657],[0,0],[1.657,0],[0,0],[0,-1.657],[0,0],[-1.657,0]],"o":[[1.657,0],[0,0],[0,-1.657],[0,0],[-1.657,0],[0,0],[0,1.657],[0,0]],"v":[[-18,21],[-15,18],[-15,-18],[-18,-21],[-42,-21],[-45,-18],[-45,18],[-42,21]],"c":true},"ix":2},"nm":"Path 2","mn":"ADBE Vector Shape - Group","hd":false},{"ind":2,"ty":"sh","ix":3,"ks":{"a":0,"k":{"i":[[0,0],[0,1.657],[0,0],[1.657,0],[0,0],[0,-1.657],[0,0],[-1.657,0]],"o":[[1.657,0],[0,0],[0,-1.657],[0,0],[-1.657,0],[0,0],[0,1.657],[0,0]],"v":[[43,21],[46,18],[46,-18],[43,-21],[19,-21],[16,-18],[16,18],[19,21]],"c":true},"ix":2},"nm":"Path 3","mn":"ADBE Vector Shape - Group","hd":false},{"ind":3,"ty":"sh","ix":4,"ks":{"a":0,"k":{"i":[[0,0],[0,1.657],[0,0],[1.657,0],[0,0],[0,-1.657],[0,0],[-1.657,0]],"o":[[1.657,0],[0,0],[0,-1.657],[0,0],[-1.657,0],[0,0],[0,1.657],[0,0]],"v":[[103,21],[106,18],[106,-18],[103,-21],[79,-21],[76,-18],[76,18],[79,21]],"c":true},"ix":2},"nm":"Path 4","mn":"ADBE Vector Shape - Group","hd":false},{"ty":"mm","mm":1,"nm":"Merge Paths 1","mn":"ADBE Vector Filter - Merge","hd":false},{"ty":"fl","c":{"a":0,"k":[0.294,0.702,0.992,1],"ix":4,"x":"var $bm_rt;\n$bm_rt = comp('wired-flat-3136-big-shop').layer('control').effect('quinary')('Color');"},"o":{"a":0,"k":100,"ix":5},"r":1,"bm":0,"nm":".quinary","mn":"ADBE Vector Graphic - Fill","hd":false,"cl":"quinary"},{"ty":"tr","p":{"a":0,"k":[0,0],"ix":2},"a":{"a":0,"k":[0,0],"ix":1},"s":{"a":0,"k":[100,100],"ix":3},"r":{"a":0,"k":0,"ix":6},"o":{"a":0,"k":100,"ix":7},"sk":{"a":0,"k":0,"ix":4},"sa":{"a":0,"k":0,"ix":5},"nm":"Transform"}],"nm":"Vector","np":6,"cix":2,"bm":0,"ix":1,"mn":"ADBE Vector Group","hd":false}],"ip":0,"op":300,"st":0,"ct":1,"bm":0},{"ddd":0,"ind":20,"ty":4,"nm":"Rectangle 94","sr":1,"ks":{"o":{"a":0,"k":100,"ix":11},"r":{"a":0,"k":0,"ix":10},"p":{"a":0,"k":[306,341.5,0],"ix":2,"l":2},"a":{"a":0,"k":[0,0,0],"ix":1,"l":2},"s":{"a":0,"k":[100,100,100],"ix":6,"l":2}},"ao":0,"shapes":[{"ty":"gr","it":[{"ind":0,"ty":"sh","ix":1,"ks":{"a":0,"k":{"i":[[0,0],[0,0],[0,0],[-1.657,0],[0,0],[0,1.657]],"o":[[0,0],[0,0],[0,1.657],[0,0],[1.657,0],[0,0]],"v":[[15,-3.5],[-15,-3.5],[-15,0.5],[-12,3.5],[12,3.5],[15,0.5]],"c":true},"ix":2},"nm":"Path 1","mn":"ADBE Vector Shape - Group","hd":false},{"ty":"fl","c":{"a":0,"k":[0.227,0.2,0.278,1],"ix":4,"x":"var $bm_rt;\n$bm_rt = comp('wired-flat-3136-big-shop').layer('control').effect('secondary')('Color');"},"o":{"a":0,"k":100,"ix":5},"r":1,"bm":0,"nm":".secondary","mn":"ADBE Vector Graphic - Fill","hd":false,"cl":"secondary"},{"ty":"tr","p":{"a":0,"k":[0,0],"ix":2},"a":{"a":0,"k":[0,0],"ix":1},"s":{"a":0,"k":[100,100],"ix":3},"r":{"a":0,"k":0,"ix":6},"o":{"a":0,"k":100,"ix":7},"sk":{"a":0,"k":0,"ix":4},"sa":{"a":0,"k":0,"ix":5},"nm":"Transform"}],"nm":"Rectangle 94","np":2,"cix":2,"bm":0,"ix":1,"mn":"ADBE Vector Group","hd":false}],"ip":0,"op":300,"st":0,"ct":1,"bm":0},{"ddd":0,"ind":21,"ty":4,"nm":"Intersect 6","sr":1,"ks":{"o":{"a":0,"k":30,"ix":11},"r":{"a":0,"k":0,"ix":10},"p":{"a":0,"k":[306,324,0],"ix":2,"l":2},"a":{"a":0,"k":[0,0,0],"ix":1,"l":2},"s":{"a":0,"k":[100,100,100],"ix":6,"l":2}},"ao":0,"shapes":[{"ty":"gr","it":[{"ind":0,"ty":"sh","ix":1,"ks":{"a":0,"k":{"i":[[0,0],[0,0],[0,-1.657],[0,0]],"o":[[0,0],[1.657,0],[0,0],[0,0]],"v":[[-9.5,-21],[12,-21],[15,-18],[15,3.5]],"c":true},"ix":2},"nm":"Path 1","mn":"ADBE Vector Shape - Group","hd":false},{"ind":1,"ty":"sh","ix":2,"ks":{"a":0,"k":{"i":[[0,0],[0,0],[0.01,1.648],[0,0]],"o":[[0,0],[-1.65,0],[0,0],[0,0]],"v":[[10.811,21],[-12,21],[-15,18.019],[-15,-4.81]],"c":true},"ix":2},"nm":"Path 2","mn":"ADBE Vector Shape - Group","hd":false},{"ty":"mm","mm":1,"nm":"Merge Paths 1","mn":"ADBE Vector Filter - Merge","hd":false},{"ty":"fl","c":{"a":0,"k":[0.922,0.902,0.937,1],"ix":4,"x":"var $bm_rt;\n$bm_rt = comp('wired-flat-3136-big-shop').layer('control').effect('primary')('Color');"},"o":{"a":0,"k":100,"ix":5},"r":1,"bm":0,"nm":".primary","mn":"ADBE Vector Graphic - Fill","hd":false,"cl":"primary"},{"ty":"tr","p":{"a":0,"k":[0,0],"ix":2},"a":{"a":0,"k":[0,0],"ix":1},"s":{"a":0,"k":[100,100],"ix":3},"r":{"a":0,"k":0,"ix":6},"o":{"a":0,"k":100,"ix":7},"sk":{"a":0,"k":0,"ix":4},"sa":{"a":0,"k":0,"ix":5},"nm":"Transform"}],"nm":"Intersect","np":4,"cix":2,"bm":0,"ix":1,"mn":"ADBE Vector Group","hd":false}],"ip":0,"op":300,"st":0,"ct":1,"bm":0},{"ddd":0,"ind":22,"ty":4,"nm":"Vector 13","sr":1,"ks":{"o":{"a":0,"k":100,"ix":11},"r":{"a":0,"k":0,"ix":10},"p":{"a":0,"k":[306,324,0],"ix":2,"l":2},"a":{"a":0,"k":[0,0,0],"ix":1,"l":2},"s":{"a":0,"k":[100,100,100],"ix":6,"l":2}},"ao":0,"shapes":[{"ty":"gr","it":[{"ind":0,"ty":"sh","ix":1,"ks":{"a":0,"k":{"i":[[0,0],[0,1.657],[0,0],[1.657,0],[0,0],[0,-1.657],[0,0],[-1.657,0]],"o":[[1.657,0],[0,0],[0,-1.657],[0,0],[-1.657,0],[0,0],[0,1.657],[0,0]],"v":[[12,21],[15,18],[15,-18],[12,-21],[-12,-21],[-15,-18],[-15,18],[-12,21]],"c":true},"ix":2},"nm":"Path 1","mn":"ADBE Vector Shape - Group","hd":false},{"ty":"rd","nm":"Round Corners 1","r":{"a":0,"k":3,"ix":1},"ix":2,"mn":"ADBE Vector Filter - RC","hd":false},{"ty":"fl","c":{"a":0,"k":[0.294,0.702,0.992,1],"ix":4,"x":"var $bm_rt;\n$bm_rt = comp('wired-flat-3136-big-shop').layer('control').effect('quinary')('Color');"},"o":{"a":0,"k":100,"ix":5},"r":1,"bm":0,"nm":".quinary","mn":"ADBE Vector Graphic - Fill","hd":false,"cl":"quinary"},{"ty":"tr","p":{"a":0,"k":[0,0],"ix":2},"a":{"a":0,"k":[0,0],"ix":1},"s":{"a":0,"k":[100,100],"ix":3},"r":{"a":0,"k":0,"ix":6},"o":{"a":0,"k":100,"ix":7},"sk":{"a":0,"k":0,"ix":4},"sa":{"a":0,"k":0,"ix":5},"nm":"Transform"}],"nm":"Vector","np":3,"cix":2,"bm":0,"ix":1,"mn":"ADBE Vector Group","hd":false}],"ip":0,"op":300,"st":0,"ct":1,"bm":0},{"ddd":0,"ind":23,"ty":4,"nm":"Vector 12","sr":1,"ks":{"o":{"a":0,"k":100,"ix":11},"r":{"a":0,"k":0,"ix":10},"p":{"a":0,"k":[124,324,0],"ix":2,"l":2},"a":{"a":0,"k":[0,0,0],"ix":1,"l":2},"s":{"a":0,"k":[100,100,100],"ix":6,"l":2}},"ao":0,"shapes":[{"ty":"gr","it":[{"ind":0,"ty":"sh","ix":1,"ks":{"a":0,"k":{"i":[[0,0],[0,1.657],[0,0],[1.657,0],[0,0],[0,-1.657],[0,0],[-1.657,0]],"o":[[1.657,0],[0,0],[0,-1.657],[0,0],[-1.657,0],[0,0],[0,1.657],[0,0]],"v":[[12,21],[15,18],[15,-18],[12,-21],[-12,-21],[-15,-18],[-15,18],[-12,21]],"c":true},"ix":2},"nm":"Path 1","mn":"ADBE Vector Shape - Group","hd":false},{"ty":"rd","nm":"Round Corners 1","r":{"a":0,"k":3,"ix":1},"ix":2,"mn":"ADBE Vector Filter - RC","hd":false},{"ty":"fl","c":{"a":0,"k":[0.294,0.702,0.992,1],"ix":4,"x":"var $bm_rt;\n$bm_rt = comp('wired-flat-3136-big-shop').layer('control').effect('quinary')('Color');"},"o":{"a":0,"k":100,"ix":5},"r":1,"bm":0,"nm":".quinary","mn":"ADBE Vector Graphic - Fill","hd":false,"cl":"quinary"},{"ty":"tr","p":{"a":0,"k":[0,0],"ix":2},"a":{"a":0,"k":[0,0],"ix":1},"s":{"a":0,"k":[100,100],"ix":3},"r":{"a":0,"k":0,"ix":6},"o":{"a":0,"k":100,"ix":7},"sk":{"a":0,"k":0,"ix":4},"sa":{"a":0,"k":0,"ix":5},"nm":"Transform"}],"nm":"Vector","np":3,"cix":2,"bm":0,"ix":1,"mn":"ADBE Vector Group","hd":false}],"ip":0,"op":300,"st":0,"ct":1,"bm":0},{"ddd":0,"ind":24,"ty":4,"nm":"Subtract 4","sr":1,"ks":{"o":{"a":0,"k":50,"ix":11},"r":{"a":0,"k":0,"ix":10},"p":{"a":0,"k":[91,157,0],"ix":2,"l":2},"a":{"a":0,"k":[0,0,0],"ix":1,"l":2},"s":{"a":0,"k":[100,100,100],"ix":6,"l":2}},"ao":0,"shapes":[{"ty":"gr","it":[{"ind":0,"ty":"sh","ix":1,"ks":{"a":0,"k":{"i":[[0,0],[0,0],[0,0],[0,0]],"o":[[0,0],[0,0],[0,0],[0,0]],"v":[[-10,58],[3.25,58],[3.25,-58],[-10,-58]],"c":true},"ix":2},"nm":"Path 1","mn":"ADBE Vector Shape - Group","hd":false},{"ty":"fl","c":{"a":0,"k":[1,0.78,0.22,1],"ix":4,"x":"var $bm_rt;\n$bm_rt = comp('wired-flat-3136-big-shop').layer('control').effect('tertiary')('Color');"},"o":{"a":0,"k":100,"ix":5},"r":1,"bm":0,"nm":".tertiary","mn":"ADBE Vector Graphic - Fill","hd":false,"cl":"tertiary"},{"ty":"tr","p":{"a":0,"k":[0,0],"ix":2},"a":{"a":0,"k":[0,0],"ix":1},"s":{"a":0,"k":[100,100],"ix":3},"r":{"a":0,"k":0,"ix":6},"o":{"a":0,"k":100,"ix":7},"sk":{"a":0,"k":0,"ix":4},"sa":{"a":0,"k":0,"ix":5},"nm":"Transform"}],"nm":"Subtract","np":2,"cix":2,"bm":0,"ix":1,"mn":"ADBE Vector Group","hd":false}],"ip":0,"op":300,"st":0,"ct":1,"bm":1},{"ddd":0,"ind":25,"ty":4,"nm":"Vector 7","sr":1,"ks":{"o":{"a":0,"k":100,"ix":11},"r":{"a":0,"k":0,"ix":10},"p":{"a":0,"k":[215.5,157,0],"ix":2,"l":2},"a":{"a":0,"k":[0,0,0],"ix":1,"l":2},"s":{"a":0,"k":[100,100,100],"ix":6,"l":2}},"ao":0,"shapes":[{"ty":"gr","it":[{"ind":0,"ty":"sh","ix":1,"ks":{"a":0,"k":{"i":[[0,0],[0,0],[0,0],[0,0]],"o":[[0,0],[0,0],[0,0],[0,0]],"v":[[133.25,58],[-134.5,58],[-134.5,-58],[133.25,-58]],"c":true},"ix":2},"nm":"Path 1","mn":"ADBE Vector Shape - Group","hd":false},{"ty":"fl","c":{"a":0,"k":[1,0.78,0.22,1],"ix":4,"x":"var $bm_rt;\n$bm_rt = comp('wired-flat-3136-big-shop').layer('control').effect('tertiary')('Color');"},"o":{"a":0,"k":100,"ix":5},"r":1,"bm":0,"nm":".tertiary","mn":"ADBE Vector Graphic - Fill","hd":false,"cl":"tertiary"},{"ty":"tr","p":{"a":0,"k":[0,0],"ix":2},"a":{"a":0,"k":[0,0],"ix":1},"s":{"a":0,"k":[100,100],"ix":3},"r":{"a":0,"k":0,"ix":6},"o":{"a":0,"k":100,"ix":7},"sk":{"a":0,"k":0,"ix":4},"sa":{"a":0,"k":0,"ix":5},"nm":"Transform"}],"nm":"Vector","np":2,"cix":2,"bm":0,"ix":1,"mn":"ADBE Vector Group","hd":false}],"ip":0,"op":300,"st":0,"ct":1,"bm":0},{"ddd":0,"ind":26,"ty":4,"nm":"Subtract 3","sr":1,"ks":{"o":{"a":0,"k":50,"ix":11},"r":{"a":0,"k":0,"ix":10},"p":{"a":0,"k":[170,55,0],"ix":2,"l":2},"a":{"a":0,"k":[0,0,0],"ix":1,"l":2},"s":{"a":0,"k":[100,100,100],"ix":6,"l":2}},"ao":0,"shapes":[{"ty":"gr","it":[{"ind":0,"ty":"sh","ix":1,"ks":{"a":0,"k":{"i":[[-1.657,0],[0,0],[0,0],[0,0],[0,1.657],[0,0]],"o":[[0,0],[0,0],[0,0],[-1.657,0],[0,0],[0,-1.657]],"v":[[-7,-19],[10,-19],[10,19],[-7,19],[-10,16],[-10,-16]],"c":true},"ix":2},"nm":"Path 1","mn":"ADBE Vector Shape - Group","hd":false},{"ty":"fl","c":{"a":0,"k":[0.922,0.902,0.937,1],"ix":4,"x":"var $bm_rt;\n$bm_rt = comp('wired-flat-3136-big-shop').layer('control').effect('primary')('Color');"},"o":{"a":0,"k":100,"ix":5},"r":1,"bm":0,"nm":".primary","mn":"ADBE Vector Graphic - Fill","hd":false,"cl":"primary"},{"ty":"tr","p":{"a":0,"k":[0,0],"ix":2},"a":{"a":0,"k":[0,0],"ix":1},"s":{"a":0,"k":[100,100],"ix":3},"r":{"a":0,"k":0,"ix":6},"o":{"a":0,"k":100,"ix":7},"sk":{"a":0,"k":0,"ix":4},"sa":{"a":0,"k":0,"ix":5},"nm":"Transform"}],"nm":"Subtract","np":2,"cix":2,"bm":0,"ix":1,"mn":"ADBE Vector Group","hd":false}],"ip":0,"op":300,"st":0,"ct":1,"bm":1},{"ddd":0,"ind":27,"ty":4,"nm":"Rectangle 91","sr":1,"ks":{"o":{"a":0,"k":100,"ix":11},"r":{"a":0,"k":0,"ix":10},"p":{"a":0,"k":[215.5,55,0],"ix":2,"l":2},"a":{"a":0,"k":[0,0,0],"ix":1,"l":2},"s":{"a":0,"k":[100,100,100],"ix":6,"l":2}},"ao":0,"shapes":[{"ty":"gr","it":[{"ind":0,"ty":"sh","ix":1,"ks":{"a":0,"k":{"i":[[0,0],[0,-1.657],[0,0],[-1.657,0],[0,0],[0,1.657],[0,0],[1.657,0]],"o":[[-1.657,0],[0,0],[0,1.657],[0,0],[1.657,0],[0,0],[0,-1.657],[0,0]],"v":[[-52.5,-19],[-55.5,-16],[-55.5,16],[-52.5,19],[52.5,19],[55.5,16],[55.5,-16],[52.5,-19]],"c":true},"ix":2},"nm":"Path 1","mn":"ADBE Vector Shape - Group","hd":false},{"ty":"rd","nm":"Round Corners 1","r":{"a":0,"k":3,"ix":1},"ix":2,"mn":"ADBE Vector Filter - RC","hd":false},{"ty":"fl","c":{"a":0,"k":[0.922,0.902,0.937,1],"ix":4,"x":"var $bm_rt;\n$bm_rt = comp('wired-flat-3136-big-shop').layer('control').effect('primary')('Color');"},"o":{"a":0,"k":100,"ix":5},"r":1,"bm":0,"nm":".primary","mn":"ADBE Vector Graphic - Fill","hd":false,"cl":"primary"},{"ty":"tr","p":{"a":0,"k":[0,0],"ix":2},"a":{"a":0,"k":[0,0],"ix":1},"s":{"a":0,"k":[100,100],"ix":3},"r":{"a":0,"k":0,"ix":6},"o":{"a":0,"k":100,"ix":7},"sk":{"a":0,"k":0,"ix":4},"sa":{"a":0,"k":0,"ix":5},"nm":"Transform"}],"nm":"Rectangle 87","np":3,"cix":2,"bm":0,"ix":1,"mn":"ADBE Vector Group","hd":false}],"ip":0,"op":300,"st":0,"ct":1,"bm":0},{"ddd":0,"ind":28,"ty":4,"nm":"Subtract 2","sr":1,"ks":{"o":{"a":0,"k":50,"ix":11},"r":{"a":0,"k":0,"ix":10},"p":{"a":0,"k":[101,77.5,0],"ix":2,"l":2},"a":{"a":0,"k":[0,0,0],"ix":1,"l":2},"s":{"a":0,"k":[100,100,100],"ix":6,"l":2}},"ao":0,"shapes":[{"ty":"gr","it":[{"ind":0,"ty":"sh","ix":1,"ks":{"a":0,"k":{"i":[[0,0],[0.492,-1.058],[0,0],[0,0],[0,0]],"o":[[-1.167,0],[0,0],[0,0],[0,0],[0,0]],"v":[[1.913,-21.5],[-0.807,-19.765],[-20,21.5],[0,21.5],[20,-21.5]],"c":true},"ix":2},"nm":"Path 1","mn":"ADBE Vector Shape - Group","hd":false},{"ty":"fl","c":{"a":0,"k":[0.227,0.2,0.278,1],"ix":4,"x":"var $bm_rt;\n$bm_rt = comp('wired-flat-3136-big-shop').layer('control').effect('secondary')('Color');"},"o":{"a":0,"k":100,"ix":5},"r":1,"bm":0,"nm":".secondary","mn":"ADBE Vector Graphic - Fill","hd":false,"cl":"secondary"},{"ty":"tr","p":{"a":0,"k":[0,0],"ix":2},"a":{"a":0,"k":[0,0],"ix":1},"s":{"a":0,"k":[100,100],"ix":3},"r":{"a":0,"k":0,"ix":6},"o":{"a":0,"k":100,"ix":7},"sk":{"a":0,"k":0,"ix":4},"sa":{"a":0,"k":0,"ix":5},"nm":"Transform"}],"nm":"Subtract","np":2,"cix":2,"bm":0,"ix":1,"mn":"ADBE Vector Group","hd":false}],"ip":0,"op":300,"st":0,"ct":1,"bm":1},{"ddd":0,"ind":29,"ty":4,"nm":"Rectangle 90","sr":1,"ks":{"o":{"a":0,"k":100,"ix":11},"r":{"a":0,"k":0,"ix":10},"p":{"a":0,"k":[215.5,77.5,0],"ix":2,"l":2},"a":{"a":0,"k":[0,0,0],"ix":1,"l":2},"s":{"a":0,"k":[100,100,100],"ix":6,"l":2}},"ao":0,"shapes":[{"ty":"gr","it":[{"ind":0,"ty":"sh","ix":1,"ks":{"a":0,"k":{"i":[[-0.492,-1.058],[0,0],[0,0],[0,0],[-1.167,0],[0,0]],"o":[[0,0],[0,0],[0,0],[0.492,-1.058],[0,0],[1.167,0]],"v":[[115.307,-19.765],[134.5,21.5],[-134.5,21.5],[-115.307,-19.765],[-112.587,-21.5],[112.587,-21.5]],"c":true},"ix":2},"nm":"Path 1","mn":"ADBE Vector Shape - Group","hd":false},{"ty":"fl","c":{"a":0,"k":[0.227,0.2,0.278,1],"ix":4,"x":"var $bm_rt;\n$bm_rt = comp('wired-flat-3136-big-shop').layer('control').effect('secondary')('Color');"},"o":{"a":0,"k":100,"ix":5},"r":1,"bm":0,"nm":".secondary","mn":"ADBE Vector Graphic - Fill","hd":false,"cl":"secondary"},{"ty":"tr","p":{"a":0,"k":[0,0],"ix":2},"a":{"a":0,"k":[0,0],"ix":1},"s":{"a":0,"k":[100,100],"ix":3},"r":{"a":0,"k":0,"ix":6},"o":{"a":0,"k":100,"ix":7},"sk":{"a":0,"k":0,"ix":4},"sa":{"a":0,"k":0,"ix":5},"nm":"Transform"}],"nm":"Rectangle 89","np":2,"cix":2,"bm":0,"ix":1,"mn":"ADBE Vector Group","hd":false}],"ip":0,"op":300,"st":0,"ct":1,"bm":0},{"ddd":0,"ind":30,"ty":4,"nm":"Vector 6","sr":1,"ks":{"o":{"a":0,"k":100,"ix":11},"r":{"a":0,"k":0,"ix":10},"p":{"a":0,"k":[215,339.5,0],"ix":2,"l":2},"a":{"a":0,"k":[0,0,0],"ix":1,"l":2},"s":{"a":0,"k":[100,100,100],"ix":6,"l":2}},"ao":0,"shapes":[{"ty":"gr","it":[{"ind":0,"ty":"sh","ix":1,"ks":{"a":0,"k":{"i":[[0,0],[0,0],[1.657,0],[0,0],[0,-1.657],[0,0]],"o":[[0,0],[0,-1.657],[0,0],[-1.657,0],[0,0],[0,0]],"v":[[37,36.5],[37,-33.5],[34,-36.5],[-34,-36.5],[-37,-33.5],[-37,36.5]],"c":false},"ix":2},"nm":"Path 1","mn":"ADBE Vector Shape - Group","hd":false},{"ind":1,"ty":"sh","ix":2,"ks":{"a":0,"k":{"i":[[0,0],[0,0]],"o":[[0,0],[0,0]],"v":[[37,36.5],[-37,36.5]],"c":false},"ix":2},"nm":"Path 2","mn":"ADBE Vector Shape - Group","hd":false},{"ty":"mm","mm":1,"nm":"Merge Paths 1","mn":"ADBE Vector Filter - Merge","hd":false},{"ty":"fl","c":{"a":0,"k":[0.922,0.902,0.937,1],"ix":4,"x":"var $bm_rt;\n$bm_rt = comp('wired-flat-3136-big-shop').layer('control').effect('primary')('Color');"},"o":{"a":0,"k":50,"ix":5},"r":1,"bm":1,"nm":".primary","mn":"ADBE Vector Graphic - Fill","hd":false,"cl":"primary"},{"ty":"fl","c":{"a":0,"k":[0.922,0.902,0.937,1],"ix":4,"x":"var $bm_rt;\n$bm_rt = comp('wired-flat-3136-big-shop').layer('control').effect('primary')('Color');"},"o":{"a":0,"k":100,"ix":5},"r":1,"bm":0,"nm":".primary","mn":"ADBE Vector Graphic - Fill","hd":false,"cl":"primary"},{"ty":"tr","p":{"a":0,"k":[0,0],"ix":2},"a":{"a":0,"k":[0,0],"ix":1},"s":{"a":0,"k":[100,100],"ix":3},"r":{"a":0,"k":0,"ix":6},"o":{"a":0,"k":100,"ix":7},"sk":{"a":0,"k":0,"ix":4},"sa":{"a":0,"k":0,"ix":5},"nm":"Transform"}],"nm":"Vector","np":5,"cix":2,"bm":0,"ix":1,"mn":"ADBE Vector Group","hd":false}],"ip":0,"op":300,"st":0,"ct":1,"bm":0},{"ddd":0,"ind":31,"ty":4,"nm":"Subtract","sr":1,"ks":{"o":{"a":0,"k":50,"ix":11},"r":{"a":0,"k":0,"ix":10},"p":{"a":0,"k":[91,312.5,0],"ix":2,"l":2},"a":{"a":0,"k":[0,0,0],"ix":1,"l":2},"s":{"a":0,"k":[100,100,100],"ix":6,"l":2}},"ao":0,"shapes":[{"ty":"gr","it":[{"ind":0,"ty":"sh","ix":1,"ks":{"a":0,"k":{"i":[[0,0],[0,0],[0,0],[-1.657,0],[0,0]],"o":[[0,0],[0,0],[0,1.657],[0,0],[0,0]],"v":[[4.219,-63.5],[-10,-63.5],[-10,60.5],[-7,63.5],[4.219,63.5]],"c":true},"ix":2},"nm":"Path 1","mn":"ADBE Vector Shape - Group","hd":false},{"ty":"fl","c":{"a":0,"k":[1,0.78,0.22,1],"ix":4,"x":"var $bm_rt;\n$bm_rt = comp('wired-flat-3136-big-shop').layer('control').effect('tertiary')('Color');"},"o":{"a":0,"k":100,"ix":5},"r":1,"bm":0,"nm":".tertiary","mn":"ADBE Vector Graphic - Fill","hd":false,"cl":"tertiary"},{"ty":"tr","p":{"a":0,"k":[0,0],"ix":2},"a":{"a":0,"k":[0,0],"ix":1},"s":{"a":0,"k":[100,100],"ix":3},"r":{"a":0,"k":0,"ix":6},"o":{"a":0,"k":100,"ix":7},"sk":{"a":0,"k":0,"ix":4},"sa":{"a":0,"k":0,"ix":5},"nm":"Transform"}],"nm":"Subtract","np":2,"cix":2,"bm":0,"ix":1,"mn":"ADBE Vector Group","hd":false}],"ip":0,"op":300,"st":0,"ct":1,"bm":1},{"ddd":0,"ind":32,"ty":4,"nm":"Rectangle 85","sr":1,"ks":{"o":{"a":0,"k":100,"ix":11},"r":{"a":0,"k":0,"ix":10},"p":{"a":0,"k":[215.5,312.5,0],"ix":2,"l":2},"a":{"a":0,"k":[0,0,0],"ix":1,"l":2},"s":{"a":0,"k":[100,100,100],"ix":6,"l":2}},"ao":0,"shapes":[{"ty":"gr","it":[{"ind":0,"ty":"sh","ix":1,"ks":{"a":0,"k":{"i":[[0,0],[0,0],[1.657,0],[0,0],[0,1.657],[0,0]],"o":[[0,0],[0,1.657],[0,0],[-1.657,0],[0,0],[0,0]],"v":[[134.5,-63.5],[134.5,60.5],[131.5,63.5],[-131.5,63.5],[-134.5,60.5],[-134.5,-63.5]],"c":true},"ix":2},"nm":"Path 1","mn":"ADBE Vector Shape - Group","hd":false},{"ty":"fl","c":{"a":0,"k":[1,0.78,0.22,1],"ix":4,"x":"var $bm_rt;\n$bm_rt = comp('wired-flat-3136-big-shop').layer('control').effect('tertiary')('Color');"},"o":{"a":0,"k":100,"ix":5},"r":1,"bm":0,"nm":".tertiary","mn":"ADBE Vector Graphic - Fill","hd":false,"cl":"tertiary"},{"ty":"tr","p":{"a":0,"k":[0,0],"ix":2},"a":{"a":0,"k":[0,0],"ix":1},"s":{"a":0,"k":[100,100],"ix":3},"r":{"a":0,"k":0,"ix":6},"o":{"a":0,"k":100,"ix":7},"sk":{"a":0,"k":0,"ix":4},"sa":{"a":0,"k":0,"ix":5},"nm":"Transform"}],"nm":"Rectangle 85","np":2,"cix":2,"bm":0,"ix":1,"mn":"ADBE Vector Group","hd":false}],"ip":0,"op":300,"st":0,"ct":1,"bm":0}]}],"layers":[{"ddd":0,"ind":1,"ty":3,"nm":"control","sr":1,"ks":{"o":{"a":0,"k":0,"ix":11},"r":{"a":0,"k":0,"ix":10},"p":{"a":0,"k":[0,0],"ix":2,"l":2},"a":{"a":0,"k":[0,0,0],"ix":1,"l":2},"s":{"a":0,"k":[100,100,100],"ix":6,"l":2}},"ao":0,"ef":[{"ty":5,"nm":"primary","np":3,"mn":"ADBE Color Control","ix":1,"en":1,"ef":[{"ty":2,"nm":"Color","mn":"ADBE Color Control-0001","ix":1,"v":{"a":0,"k":[0.922,0.902,0.937],"ix":1}}]},{"ty":5,"nm":"secondary","np":3,"mn":"ADBE Color Control","ix":2,"en":1,"ef":[{"ty":2,"nm":"Color","mn":"ADBE Color Control-0001","ix":1,"v":{"a":0,"k":[0.227,0.2,0.278],"ix":1}}]},{"ty":5,"nm":"tertiary","np":3,"mn":"ADBE Color Control","ix":3,"en":1,"ef":[{"ty":2,"nm":"Color","mn":"ADBE Color Control-0001","ix":1,"v":{"a":0,"k":[1,0.78,0.22],"ix":1}}]},{"ty":5,"nm":"quaternary","np":3,"mn":"ADBE Color Control","ix":4,"en":1,"ef":[{"ty":2,"nm":"Color","mn":"ADBE Color Control-0001","ix":1,"v":{"a":0,"k":[0.573,0.078,0.047],"ix":1}}]},{"ty":5,"nm":"quinary","np":3,"mn":"ADBE Color Control","ix":5,"en":1,"ef":[{"ty":2,"nm":"Color","mn":"ADBE Color Control-0001","ix":1,"v":{"a":0,"k":[0.294,0.702,0.992],"ix":1}}]}],"ip":0,"op":168,"st":0,"bm":0},{"ddd":0,"ind":3,"ty":0,"nm":"hover-pinch","refId":"comp_1","sr":1,"ks":{"o":{"a":0,"k":100,"ix":11},"r":{"a":0,"k":0,"ix":10},"p":{"a":0,"k":[215,215,0],"ix":2,"l":2},"a":{"a":0,"k":[215,215,0],"ix":1,"l":2},"s":{"a":0,"k":[100,100,100],"ix":6,"l":2}},"ao":0,"w":430,"h":430,"ip":0,"op":100,"st":0,"bm":0,"layers":[]}],"markers":[{"tm":0,"cm":"default:hover-pinch","dr":90}],"props":{}}